{"id":150,"title":"Dv\u0113sle s\u0101p\u0113s asi kliedz","body":"","bodyLyrics":"","bodyAbc":"","url":"\/song\/150-Valda_Zaberga_-_Dvesle_Sapes_Asi_Kliedz","youtubeLink":"","updatedDate":"2022-02-26T16:21:01Z","createdDate":"2007-02-27T22:00:00Z","songTop":{"visitsWeekly":0},"mainArtist":{"id":44,"title":"Valda Z\u0101berga","url":"\/band\/44-Valda_Zaberga","songCount":1,"updatedDate":"2022-02-26T16:19:11Z","createdDate":"2007-02-27T22:00:00Z"},"tags":[],"poets":null,"composers":null,"performers":null}