{"id":4928,"title":"Dzintara meitene","body":"C G D G\n\n[G] Toreiz Tu teici, ka m\u012bl\u0113sim m\u016b\u017eam,\nTom\u0113r t\u0101 notikt mums [D] nebija lemts.\nViens pats es paliku likteni l\u016bdzam,\nDaudz man no laimes un [G] m\u012blas bij \u0146emts.\n\n2x\n[G] Tagad p\u0113c gadiem, kad [C] ieraugu Tevi,\nAtmi\u0146as plos\u0101s un [G] nesp\u0113j t\u0101s rimt.\nIeklausos likten\u012b, [D] ieklausos sev\u012b,\nKaut kas no jauna man [G] kr\u016bt\u012bs s\u0101k dzimt.\n\n[G] St\u0101sti, k\u0101 g\u0101jis un nesl\u0113p ne nieka,\nBiji, vai nebiji, [D] laim\u012bga Tu?\nNez, vai par mani Tev vair\u0101k bij prieka?\nAk, lai nu paliek, [G] es saprotu.\n\n2x\n[G] Pasmaidi, dzintara [C] meitene mana,\nMatos Tev zeltaini [G] saulstari mirdz.\nTevi es m\u012blu, j\u0101 [D] m\u012blu bez gala,\nVienm\u0113r p\u0113c Tevis man [G] ilgojas sirds.\n\nG D G C G D G E\n\n[A] S\u0101ksim, ja gribi, m\u0113s visu no jauna,\nPag\u0101tnes murgi, lai [E] atmi\u0146\u0101m, gaist.\nDz\u012bve patie\u0161\u0101m nemaz nav tik \u013cauna,\nAizlauztie koki var [A] atvases laist.\n\n2x\n[A] Pasmaidi, dzintara [D] meitene mana,\nMatos Tev zeltaini [A] saulstari mirdz.\nTevi es m\u012blu, j\u0101 [E] m\u012blu bez gala,\nVienm\u0113r p\u0113c Tevis man [A] ilgojas sirds.\n\n[A] Tevi es m\u012blu, j\u0101 [E] m\u012blu bez gala,\nVienm\u0113r p\u0113c Tevis man [A] ilgojas sirds.\n","bodyLyrics":"Toreiz Tu teici, ka m\u012bl\u0113sim m\u016b\u017eam,\nTom\u0113r t\u0101 notikt mums nebija lemts.\nViens pats es paliku likteni l\u016bdzam,\nDaudz man no laimes un m\u012blas bij \u0146emts.\n\n2x\nTagad p\u0113c gadiem, kad ieraugu Tevi,\nAtmi\u0146as plos\u0101s un nesp\u0113j t\u0101s rimt.\nIeklausos likten\u012b, ieklausos sev\u012b,\nKaut kas no jauna man kr\u016bt\u012bs s\u0101k dzimt.\n\nSt\u0101sti, k\u0101 g\u0101jis un nesl\u0113p ne nieka,\nBiji, vai nebiji, laim\u012bga Tu?\nNez, vai par mani Tev vair\u0101k bij prieka?\nAk, lai nu paliek, es saprotu.\n\n2x\nPasmaidi, dzintara meitene mana,\nMatos Tev zeltaini saulstari mirdz.\nTevi es m\u012blu, j\u0101 m\u012blu bez gala,\nVienm\u0113r p\u0113c Tevis man ilgojas sirds.\n\n\nS\u0101ksim, ja gribi, m\u0113s visu no jauna,\nPag\u0101tnes murgi, lai atmi\u0146\u0101m, gaist.\nDz\u012bve patie\u0161\u0101m nemaz nav tik \u013cauna,\nAizlauztie koki var atvases laist.\n\n2x\nPasmaidi, dzintara meitene mana,\nMatos Tev zeltaini saulstari mirdz.\nTevi es m\u012blu, j\u0101 m\u012blu bez gala,\nVienm\u0113r p\u0113c Tevis man ilgojas sirds.\n\nTevi es m\u012blu, j\u0101 m\u012blu bez gala,\nVienm\u0113r p\u0113c Tevis man ilgojas sirds.","bodyAbc":"","url":"\/song\/4928-Aigarins_-_Dzintara_Meitene","youtubeLink":"","updatedDate":"2022-09-19T06:12:49Z","createdDate":"2022-09-19T06:12:49Z","songTop":{"visitsWeekly":0},"mainArtist":{"id":1642,"title":"Aigari\u0146\u0161","url":"\/band\/1642-Aigarins","songCount":4,"updatedDate":"2023-05-03T04:13:24.225Z","createdDate":"2020-06-05T15:21:19Z"},"tags":[],"poets":[{"id":1864,"title":"Aigars Ik\u0161elis","url":"\/band\/1864-Aigars_Ikselis","songCount":1,"updatedDate":"2023-05-03T04:13:13.327Z","createdDate":"2022-09-19T06:12:50Z"}],"composers":[{"id":1864,"title":"Aigars Ik\u0161elis","url":"\/band\/1864-Aigars_Ikselis","songCount":1,"updatedDate":"2023-05-03T04:13:13.327Z","createdDate":"2022-09-19T06:12:50Z"}],"performers":[{"id":1642,"title":"Aigari\u0146\u0161","url":"\/band\/1642-Aigarins","songCount":4,"updatedDate":"2023-05-03T04:13:24.225Z","createdDate":"2020-06-05T15:21:19Z"}]}