{"id":3180,"title":"Always","body":"I tried to find an answer in every thing you said\r\nno emptiness in all those dreams that we both had made\r\nI\u2019m running down those streets and the sky is crashing on me\r\nis that satisfaction for you to show how brave you are ..\r\n\r\ndon\u2019t run away\r\ndon\u2019t break me down\r\n\u2018cause I\u2019ve always loved you\r\nAnd I always will .. and I ..\r\n\r\nsometimes I think that your mind is acting against the \r\nfeelings in your heart\r\nI know I\u2019m not a perfect person but at least I\u2019m true \r\nto myself\r\nevery night in my dreams you are there \u2013 so close\r\none thing I know for sure if you will need me I\u2019ll be \r\nthere by your side ..\r\n\r\ndon\u2019t run away\r\ndon\u2019t break me down\r\n\u2018cause I\u2019ve always loved you\r\nAnd I always will .. and I ..\r\n\r\nsomebody said love\u2019s just a feelin\u2019\r\nbut without it can you be alive\r\nlove is most beautiful feelin\u2019\r\nyou can have in this world .\r\n\r\ndon\u2019t run away\r\ndon\u2019t break me down\r\n\u2018cause I\u2019ve always loved you\r\nAnd I always will .. and I ..","bodyLyrics":"I tried to find an answer in every thing you said\r\nno emptiness in all those dreams that we both had made\r\nI\u2019m running down those streets and the sky is crashing on me\r\nis that satisfaction for you to show how brave you are ..\r\n\r\ndon\u2019t run away\r\ndon\u2019t break me down\r\n\u2018cause I\u2019ve always loved you\r\nAnd I always will .. and I ..\r\n\r\nsometimes I think that your mind is acting against the \r\nfeelings in your heart\r\nI know I\u2019m not a perfect person but at least I\u2019m true \r\nto myself\r\nevery night in my dreams you are there \u2013 so close\r\none thing I know for sure if you will need me I\u2019ll be \r\nthere by your side ..\r\n\r\ndon\u2019t run away\r\ndon\u2019t break me down\r\n\u2018cause I\u2019ve always loved you\r\nAnd I always will .. and I ..\r\n\r\nsomebody said love\u2019s just a feelin\u2019\r\nbut without it can you be alive\r\nlove is most beautiful feelin\u2019\r\nyou can have in this world .\r\n\r\ndon\u2019t run away\r\ndon\u2019t break me down\r\n\u2018cause I\u2019ve always loved you\r\nAnd I always will .. and I ..","bodyAbc":"","url":"\/song\/3180-Enas_-_Always","youtubeLink":"Xbz4lCqtwMw","updatedDate":"2024-03-17T01:43:15.1234Z","createdDate":"2017-11-26T11:30:51Z","songTop":{"visitsWeekly":0},"mainArtist":{"id":79,"title":"\u0112nas","url":"\/band\/79-Enas","songCount":25,"updatedDate":"2022-02-26T16:19:11Z","createdDate":"2007-11-12T22:00:00Z"},"tags":[{"id":16,"title":"eng","url":"\/tag\/16-Eng","songCount":311,"labelColor":"#18bc9c"},{"id":22,"title":"bez akordiem","url":"\/tag\/22-Bez_Akordiem","songCount":1535,"labelColor":"#95a5a6"}],"poets":[{"id":774,"title":"Lauris Valters","url":"\/band\/774-Lauris_Valters","songCount":22,"updatedDate":"2022-02-26T16:19:11Z","createdDate":"2016-03-11T15:51:30Z"}],"composers":[],"performers":[{"id":79,"title":"\u0112nas","url":"\/band\/79-Enas","songCount":25,"updatedDate":"2022-02-26T16:19:11Z","createdDate":"2007-11-12T22:00:00Z"}]}