{"id":1877,"title":"Ruksis rik\u0161ot\u0101js","body":"tas ruksis b\u016bs rik\u0161ot\u0101js\r\nman\u0101 lauk\u0101 d\u0101rzs pa pliko\r\ntas ruksis b\u016bs rik\u0161ot\u0101js\r\nsavai draudzenei pa pliko\r\ntas ruksis b\u016bs rik\u0161ot\u0101js\r\nkas dab\u016bs ar\u012b pats pa pliko\r\n\r\n\u016b \u016b \u016b\r\nlai skan garais \u016b\r\n\r\nmana m\u0101sa ir s\u0113\u0146ot\u0101js\r\nme\u017e\u0101 viegli brien pa pliko\r\nmana m\u0101sa nav rik\u0161ot\u0101js\r\napmald\u0101s pa pliko\r\nm\u0101sa atkal b\u016bs s\u0113\u0146ot\u0101js\r\nkop\u0101 iesim bekot pa pliko\r\n\r\n\u016b \u016b \u016b\r\nlai skan garais \u016b","bodyLyrics":"tas ruksis b\u016bs rik\u0161ot\u0101js\nman\u0101 lauk\u0101 d\u0101rzs pa pliko\ntas ruksis b\u016bs rik\u0161ot\u0101js\nsavai draudzenei pa pliko\ntas ruksis b\u016bs rik\u0161ot\u0101js\nkas dab\u016bs ar\u012b pats pa pliko\n\n\u016b \u016b \u016b\nlai skan garais \u016b\n\nmana m\u0101sa ir s\u0113\u0146ot\u0101js\nme\u017e\u0101 viegli brien pa pliko\nmana m\u0101sa nav rik\u0161ot\u0101js\napmald\u0101s pa pliko\nm\u0101sa atkal b\u016bs s\u0113\u0146ot\u0101js\nkop\u0101 iesim bekot pa pliko\n\n\u016b \u016b \u016b\nlai skan garais \u016b","bodyAbc":"","url":"\/song\/1877-Labveligais_Tips_-_Ruksis_Riksotajs","youtubeLink":"","updatedDate":"2022-02-26T16:21:10Z","createdDate":"2014-09-11T11:40:46Z","songTop":{"visitsWeekly":0},"mainArtist":{"id":6,"title":"Labv\u0113l\u012bgais Tips","url":"\/band\/6-Labveligais_Tips","songCount":62,"updatedDate":"2023-06-19T13:53:56.757Z","createdDate":"2022-12-06T07:42:49Z"},"tags":[{"id":22,"title":"bez akordiem","url":"\/tag\/22-Bez_Akordiem","songCount":1535,"labelColor":"#95a5a6"}],"poets":[{"id":6,"title":"Labv\u0113l\u012bgais Tips","url":"\/band\/6-Labveligais_Tips","songCount":62,"updatedDate":"2023-06-19T13:53:56.757Z","createdDate":"2022-12-06T07:42:49Z"}],"composers":[{"id":6,"title":"Labv\u0113l\u012bgais Tips","url":"\/band\/6-Labveligais_Tips","songCount":62,"updatedDate":"2023-06-19T13:53:56.757Z","createdDate":"2022-12-06T07:42:49Z"}],"performers":[{"id":6,"title":"Labv\u0113l\u012bgais Tips","url":"\/band\/6-Labveligais_Tips","songCount":62,"updatedDate":"2023-06-19T13:53:56.757Z","createdDate":"2022-12-06T07:42:49Z"}]}