{"id":4834,"title":"Sien\u0101z\u012btis - muzikants","body":"Em D A D\n\nD    A    D\nZ\u0101l\u0113 \u010d\u012bg\u0101 sien\u0101z\u012btis\nD\nVienm\u0113r jautrais vijolnieks\nD     A     D\nJauka \u0161ogad vasari\u0146a\nD\nAr\u012b vi\u0146am t\u0101p\u0113c prieks\n\nPiedz.\nG            D\nSp\u0113l\u0113, sp\u0113l\u0113 sien\u0101z\u012bti\nA         D\nSilto vasari\u0146u sveic\nG           D\nTavi draugi klaus\u0101s tevi\nA          D\nRaiti savu darbu veic\n\nSkudras \u010daklas namdar\u012btes\nSkujas nes un namu ce\u013c\nZiedu p\u013cav\u0101 darba bites\nSaldu meduti\u0146u sme\u013c\n\nPiedz.\n\n\n\n\n","bodyLyrics":"Z\u0101l\u0113 \u010d\u012bg\u0101 sien\u0101z\u012btis\nVienm\u0113r jautrais vijolnieks\nJauka \u0161ogad vasari\u0146a\nAr\u012b vi\u0146am t\u0101p\u0113c prieks\n\nPiedz.\nSp\u0113l\u0113, sp\u0113l\u0113 sien\u0101z\u012bti\nSilto vasari\u0146u sveic\nTavi draugi klaus\u0101s tevi\nRaiti savu darbu veic\n\nSkudras \u010daklas namdar\u012btes\nSkujas nes un namu ce\u013c\nZiedu p\u013cav\u0101 darba bites\nSaldu meduti\u0146u sme\u013c\n\nPiedz.","bodyAbc":"","url":"\/song\/4834-Arvids_Zilinskis_-_Sienazitis_-_Muzikants","youtubeLink":"succASgK-RA","updatedDate":"2022-02-26T16:21:30Z","createdDate":"2021-10-25T12:46:51Z","songTop":{"visitsWeekly":0},"mainArtist":{"id":323,"title":"Arv\u012bds \u017dilinskis","url":"\/band\/323-Arvids_Zilinskis","songCount":5,"updatedDate":"2022-02-26T16:19:11Z","createdDate":"2021-10-25T12:47:40Z"},"tags":[{"id":20,"title":"b\u0113rnu","url":"\/tag\/20-Bernu","songCount":24,"labelColor":"#18bc9c"}],"poets":[],"composers":[{"id":323,"title":"Arv\u012bds \u017dilinskis","url":"\/band\/323-Arvids_Zilinskis","songCount":5,"updatedDate":"2022-02-26T16:19:11Z","createdDate":"2021-10-25T12:47:40Z"}],"performers":[{"id":323,"title":"Arv\u012bds \u017dilinskis","url":"\/band\/323-Arvids_Zilinskis","songCount":5,"updatedDate":"2022-02-26T16:19:11Z","createdDate":"2021-10-25T12:47:40Z"}]}