{"id":748,"title":"Dziesmi\u0146a dziedama pus\u010detros no r\u012bta","body":"   Am     \nPa\u0146em sev \u0161o violeto debesi\nUn \u0161os m\u0101ko\u0146sodr\u0113jus...\nNav jau diezkas, nav jau diezkas,\nBet varb\u016bt, ka noder\u0113s!\n\n  C\nPa\u0146em pa\u0146em manu nogurumu,\nEs, es pie tevis gribu.\n   F                     Fm F\nMan vienalga, K\u0101 to sauc,\n C\nVar, var ar\u012b par m\u012blest\u012bbu.\n\n Ab                      Eb\nEs tev, es tev neprasu nemaz\n Ab                      Eb\nPasauli pasauli \u0161o piesild\u012bt.\n Ab                          Eb\nTad jau, tad jau n\u0101kamaj\u0101 br\u012bd\u012b\n Ab            Eb\nPiepras\u012btu piepild\u012bt.\n\n  C\nPa\u0146em pa\u0146em manu nogurumu,\nEs, es pie tevis gribu, gribu, gribu.\n   F                    Fm F\nMan vienalga, k\u0101 to sauc,\n C\nVar, var ar\u012b par m\u012blest\u012bbu.\n\n   Am\nNav jau diez kas, nav jau diez kas,\nBet varb\u016bt, ka noder\u0113s.\nPa\u0146em sev \u0161o violeto debesi\nUn \u0161os m\u0101ko\u0146sodr\u0113jus.\n\npantiem da\u017e\u0101di taktsm\u0113ri:12\/8, 4\/4,","bodyLyrics":"M\u016bzika: Imants Kalni\u0146\u0161\r\nV\u0101rdi: M\u0101ris \u010caklais\r\nIzpild\u012bt\u0101js: Menuets\r\n\r\nPa\u0146em sev \u0161o violeto debesi\r\nUn \u0161os m\u0101ko\u0146sodr\u0113jus...\r\nNav jau diezkas, nav jau diezkas,\r\nBet varb\u016bt, ka noder\u0113s!\r\n\r\nPa\u0146em pa\u0146em manu nogurumu,\r\nEs, es pie tevis gribu.\r\nMan vienalga, K\u0101 to sauc,\r\nVar, var ar\u012b par m\u012blest\u012bbu.\r\n\r\nEs tev, es tev neprasu nemaz\r\nPasauli pasauli \u0161o piesild\u012bt.\r\nTad jau, tad jau n\u0101kamaj\u0101 br\u012bd\u012b\r\nPiepras\u012btu piepild\u012bt.\r\n\r\nPa\u0146em pa\u0146em manu nogurumu,\r\nEs, es pie tevis gribu, gribu, gribu.\r\nMan vienalga, k\u0101 to sauc,\r\nVar, var ar\u012b par m\u012blest\u012bbu.\r\n\r\nNav jau diez kas, nav jau diez kas,\r\nBet varb\u016bt, ka noder\u0113s.\r\nPa\u0146em sev \u0161o violeto debesi\r\nUn \u0161os m\u0101ko\u0146sodr\u0113jus.\r\n\r\npantiem da\u017e\u0101di taktsm\u0113ri:12\/8, 4\/4,\r\n\r\n\r\nForum\u0101 ievietoja mru","bodyAbc":"","url":"\/song\/748-Menuets_-_Dziesmina_Dziedama_Puscetros_No_Rita","youtubeLink":"nokgbPp8TJQ","updatedDate":"2022-02-26T16:21:05Z","createdDate":"2008-08-08T21:00:00Z","songTop":{"visitsWeekly":1},"mainArtist":{"id":205,"title":"Menuets","url":"\/band\/205-Menuets","songCount":22,"updatedDate":"2023-09-25T19:47:10.378Z","createdDate":"2021-08-05T09:23:24Z"},"tags":[],"poets":[{"id":352,"title":"M\u0101ris \u010caklais","url":"\/band\/352-Maris_Caklais","songCount":30,"updatedDate":"2023-11-15T11:09:29.027Z","createdDate":"2014-07-14T21:00:00Z"}],"composers":[{"id":14,"title":"Imants Kalni\u0146\u0161","url":"\/band\/14-Imants_Kalnins","songCount":119,"updatedDate":"2023-10-04T19:16:42.774Z","createdDate":"2023-01-24T09:22:56.732Z"}],"performers":[{"id":205,"title":"Menuets","url":"\/band\/205-Menuets","songCount":22,"updatedDate":"2023-09-25T19:47:10.378Z","createdDate":"2021-08-05T09:23:24Z"}]}