{"id":89,"title":"Saldus Saule","body":"(J\u0101dziet l\u0113nu un zemu.)\n\nF      Em          Dm      \nRuden\u012b vi\u0146a k\u0101 rupjmaize,\nGm         C        F\nSiltiem gabaliem lau\u017eama\nF      Em         Dm      \nZiem\u0101 kabat\u0101 sild\u012bta \nGm          C        F\nEs vi\u0146u k\u0101 burk\u0101nu grau\u017eu\n\nF      Em          Dm     \nVasar\u0101 b\u0113rniem galvi\u0146as \nGm         C        F\nVi\u0146a tik m\u012b\u013ci piegl\u0101sta\nF      Em          Dm   \nKa atn\u0101kam gaid\u012b\u0161anai\nGm         C        F\nK\u013c\u016bst tik pavasar' viegla\n\n\n     Gm           Am            Dm    Bb          C            Dm        \nP:   Saule , ko vienreiz var ieg\u016bt, saule , ko nevar vairs zaud\u0113t        \n     Gm           Am           Dm     Bb                     Am        Bb          C \n     Saule , ko vienreiz var ieg\u016bt, saule , ko nevar vairs zaud\u0113t   \n\nF      Em         Dm \nP\u0101ri kalns\u0113tas kokiem austo\u0161a\nGm         C        F\nVisur l\u012bdzi t\u0101 bijusi\nF      Em         Dm \nMana zelta kontrabanda\nGm          C        F\nMana kabatas baterija\n\n\nP:   Gm           Am            Dm    Bb          C            Dm   \nP:   Saule , ko vienreiz var ieg\u016bt, saule , ko nevar vairs zaud\u0113t        \n     Gm           Am           Dm     Bb                     Am        Bb          C \n     Saule , ko vienreiz var ieg\u016bt, saule , ko nevar vairs zaud\u0113t   \n\n<p class=\"text-muted\">Pilnu dziesmas Guitar Pro versiju var lejupiel\u0101d\u0113t \u0161eit:\nhttps:\/\/www.akordi.lv\/faili\/pro\/Livi-Saldus_Saule.gp5\nGuitar Pro tabus veidojis Oskars Kalnins\nRoberts & Andris<\/p>","bodyLyrics":"(J\u0101dziet l\u0113nu un zemu.)\n\nRuden\u012b vi\u0146a k\u0101 rupjmaize,\nSiltiem gabaliem lau\u017eama\nZiem\u0101 kabat\u0101 sild\u012bta \nEs vi\u0146u k\u0101 burk\u0101nu grau\u017eu\n\nVasar\u0101 b\u0113rniem galvi\u0146as \nVi\u0146a tik m\u012b\u013ci piegl\u0101sta\nKa atn\u0101kam gaid\u012b\u0161anai\nK\u013c\u016bst tik pavasar' viegla\n\n\nP: Saule , ko vienreiz var ieg\u016bt, saule , ko nevar vairs zaud\u0113t \nSaule , ko vienreiz var ieg\u016bt, saule , ko nevar vairs zaud\u0113t \n\nP\u0101ri kalns\u0113tas kokiem austo\u0161a\nVisur l\u012bdzi t\u0101 bijusi\nMana zelta kontrabanda\nMana kabatas baterija\n\n\nP: Saule , ko vienreiz var ieg\u016bt, saule , ko nevar vairs zaud\u0113t \nSaule , ko vienreiz var ieg\u016bt, saule , ko nevar vairs zaud\u0113t \n\n<p class=\"text-muted\">Pilnu dziesmas Guitar Pro versiju var lejupiel\u0101d\u0113t \u0161eit:\nhttps:\/\/www.akordi.lv\/faili\/pro\/Livi-Saldus_Saule.gp5\nGuitar Pro tabus veidojis Oskars Kalnins\nRoberts & Andris<\/p>","bodyAbc":"","url":"\/song\/89-Livi_-_Saldus_Saule","youtubeLink":"kun8v1GdfBU","updatedDate":"2023-07-12T15:25:46.239Z","createdDate":"2007-02-26T22:00:00Z","songTop":{"visitsWeekly":5},"mainArtist":{"id":2,"title":"L\u012bvi","url":"\/band\/2-Livi","songCount":85,"updatedDate":"2023-09-30T15:23:52.415Z","createdDate":"2022-11-10T20:56:32Z"},"tags":[{"id":12,"title":"guitar pro","url":"\/tag\/12-Guitar_Pro","songCount":6,"labelColor":"#3498db"}],"poets":[{"id":352,"title":"M\u0101ris \u010caklais","url":"\/band\/352-Maris_Caklais","songCount":30,"updatedDate":"2023-11-15T11:09:29.027Z","createdDate":"2014-07-14T21:00:00Z"},{"id":813,"title":"M\u0101ris \u0160verns","url":"\/band\/813-Maris_Sverns","songCount":12,"updatedDate":"2023-03-06T12:07:22.553Z","createdDate":"2016-04-18T20:54:39Z"}],"composers":[{"id":326,"title":"\u0112riks \u0136i\u0123elis","url":"\/band\/326-Eriks_Kigelis","songCount":9,"updatedDate":"2023-07-12T15:26:05.933Z","createdDate":"2014-07-13T21:00:00Z"},{"id":813,"title":"M\u0101ris \u0160verns","url":"\/band\/813-Maris_Sverns","songCount":12,"updatedDate":"2023-03-06T12:07:22.553Z","createdDate":"2016-04-18T20:54:39Z"}],"performers":[{"id":2,"title":"L\u012bvi","url":"\/band\/2-Livi","songCount":85,"updatedDate":"2023-09-30T15:23:52.415Z","createdDate":"2022-11-10T20:56:32Z"},{"id":30,"title":"Balo\u017eu Pilni Pagalmi","url":"\/band\/30-Balozu_Pilni_Pagalmi","songCount":17,"updatedDate":"2023-03-06T12:07:06.528Z","createdDate":"2007-02-26T22:00:00Z"}]}