{"id":2786,"title":"Prom No","body":"Virs galvas lido dz\u0113rves prom\r\nDz\u0113rv\u0113m nav \u0161eit vietas\r\nBet varb\u016bt lidot prom t\u0101m piederas pie lietas\r\n\r\nNo pel\u0113c\u012bbas, pel\u0113c\u012bbas ,pel\u0113c\u012bbas prom,\r\nNo pel\u0113c\u012bbas, pel\u0113c\u012bbas ,pel\u0113c\u012bbas prom,\r\nNo pel\u0113c\u012bbas prom\r\n\r\nZem  tilta n\u0101rsto la\u0161i prom,\r\nLa\u0161iem nav \u0161eit vietas,\r\nBet varb\u016bt peld\u0113t prom tiem piederas pie lietas\r\n\r\nNo garlaic\u012bbas, garlaic\u012bbas, garlaic\u012bbas prom,\r\nNo garlaic\u012bbas, garlaic\u012bbas, garlaic\u012bbas prom,\r\nNo garlaic\u012bbas prom\r\n\r\nAizaug lauki, paliek m\u0101jas\r\nM\u0113s dodamies prom \r\nMums vairs nav \u0161eit vietas\r\nBet varb\u016bt doties prom mums piederas pie lietas \r\nBet varb\u016bt doties prom mums piederas pie lietas \r\nProm no pel\u0113\u010dibas, pel\u0113c\u012bbas, pel\u0113c\u012bbas\r\nProm no garlaic\u012bbas, garlaic\u012bbas, garlaic\u012bbas \r\nProm no nolemt\u012bbas\r\nBet ko Tu te v\u0113l dari ? \r\n\r\nVirs galvas lido dz\u0113rves prom\r\nDz\u0113rv\u0113m nav \u0161eit vietas\r\nBet varb\u016bt lidot prom t\u0101m piederas pie lietas","bodyLyrics":"Virs galvas lido dz\u0113rves prom\nDz\u0113rv\u0113m nav \u0161eit vietas\nBet varb\u016bt lidot prom t\u0101m piederas pie lietas\n\nNo pel\u0113c\u012bbas, pel\u0113c\u012bbas ,pel\u0113c\u012bbas prom,\nNo pel\u0113c\u012bbas, pel\u0113c\u012bbas ,pel\u0113c\u012bbas prom,\nNo pel\u0113c\u012bbas prom\n\nZem tilta n\u0101rsto la\u0161i prom,\nLa\u0161iem nav \u0161eit vietas,\nBet varb\u016bt peld\u0113t prom tiem piederas pie lietas\n\nNo garlaic\u012bbas, garlaic\u012bbas, garlaic\u012bbas prom,\nNo garlaic\u012bbas, garlaic\u012bbas, garlaic\u012bbas prom,\nNo garlaic\u012bbas prom\n\nAizaug lauki, paliek m\u0101jas\nM\u0113s dodamies prom \nMums vairs nav \u0161eit vietas\nBet varb\u016bt doties prom mums piederas pie lietas \nBet varb\u016bt doties prom mums piederas pie lietas \nProm no pel\u0113\u010dibas, pel\u0113c\u012bbas, pel\u0113c\u012bbas\nProm no garlaic\u012bbas, garlaic\u012bbas, garlaic\u012bbas \nProm no nolemt\u012bbas\nBet ko Tu te v\u0113l dari ? \n\nVirs galvas lido dz\u0113rves prom\nDz\u0113rv\u0113m nav \u0161eit vietas\nBet varb\u016bt lidot prom t\u0101m piederas pie lietas","bodyAbc":"","url":"\/song\/2786-Gapoljeri_-_Prom_No","youtubeLink":"","updatedDate":"2022-02-26T16:21:16Z","createdDate":"2016-09-08T08:39:12Z","songTop":{"visitsWeekly":0},"mainArtist":{"id":841,"title":"Gapoljeri","url":"\/band\/841-Gapoljeri","songCount":7,"updatedDate":"2022-02-26T16:19:11Z","createdDate":"2016-05-20T06:19:57Z"},"tags":[{"id":22,"title":"bez akordiem","url":"\/tag\/22-Bez_Akordiem","songCount":1535,"labelColor":"#95a5a6"}],"poets":[{"id":841,"title":"Gapoljeri","url":"\/band\/841-Gapoljeri","songCount":7,"updatedDate":"2022-02-26T16:19:11Z","createdDate":"2016-05-20T06:19:57Z"}],"composers":[{"id":841,"title":"Gapoljeri","url":"\/band\/841-Gapoljeri","songCount":7,"updatedDate":"2022-02-26T16:19:11Z","createdDate":"2016-05-20T06:19:57Z"}],"performers":[{"id":841,"title":"Gapoljeri","url":"\/band\/841-Gapoljeri","songCount":7,"updatedDate":"2022-02-26T16:19:11Z","createdDate":"2016-05-20T06:19:57Z"}]}