{"id":1676,"title":"P\u0101riet Bailes","body":"Intro: C Em Am G\n\n   C\t\t\nKo gaida b\u0113rza pumpuri\u0146\u0161,\n    Em\nKad atombumbai smaida vi\u0146\u0161?\n   Am\t\t\t   G\nEs biju, tads es mazliet biju.\n    C\nMan asti luncin\u0101t - k\u0101ds prieks!\n   Em\nEs biju jomas teicamnieks.\n   Am\t\t       G\nIk nakti, katru m\u012b\u013cu nakti.\n\n        F\t  Am\nAr seju snieg\u0101.\n\t C\t  G\nAr seju snieg\u0101.\n\n   C\t\t\nKur\u0161 nem\u0101k v\u0101rdus nosarg\u0101t,\n    Em\nUz f\u0101rmklubu tiek aizg\u0101d\u0101ts \n   Am\t\t\t   G\nT\u0101ds likums, t\u0101ds ir m\u016b\u017e\u012bgs likums.\n    C\nTu noklus\u0113si draudzen\u0113m,\n   Em\nTu nosl\u0113psies aiz sl\u0113dzen\u0113m,\n   Am\t\t       G\nTu drupsi, katru dienu drupsi.\n\n        F\t  Am\nAr seju snieg\u0101.\n\t C\t  G\nAr seju snieg\u0101. (2x)\n\nPiedz:\n\t    C\nS\u0101k p\u0101riet bailes,\n\tEm\nP\u0101riet bailes\n\tAm\nP\u0101riet bailes\n\tF\nP\u0101riet Oohhoooo\n\n\n   C\t\t\nNav karma b\u0113bis nevar\u012bgs,\n    Em\nT\u0101s kodiens esot ne\u017e\u0113l\u012bgs,\n   Am\t\t\t   G\nPlus inde, n\u0101v\u0113jo\u0161a inde.\n    C\nK\u0101ds atraus m\u016bsu libido,\n   Em\nAr spai\u0146iem \u0146ems un sasmels to.\n   Am\t\t       G\nCik stulbi! Ak, cik tas ir stulbi!\n\n        F\t  Am\nAr seju snieg\u0101.\n\t C\t  G\nAr seju snieg\u0101. (x2)\n\n\t    C\nS\u0101k p\u0101riet bailes,\n\tEm\nP\u0101riet bailes...  (x6)","bodyLyrics":"Ko gaida b\u0113rza pumpuri\u0146\u0161,\nKad atombumbai smaida vi\u0146\u0161?\nEs biju, tads es mazliet biju.\nMan asti luncin\u0101t - k\u0101ds prieks!\nEs biju jomas teicamnieks.\nIk nakti, katru m\u012b\u013cu nakti.\n\nAr seju snieg\u0101.\nAr seju snieg\u0101.\n\nKur\u0161 nem\u0101k v\u0101rdus nosarg\u0101t,\nUz f\u0101rmklubu tiek aizg\u0101d\u0101ts \nT\u0101ds likums, t\u0101ds ir m\u016b\u017e\u012bgs likums.\nTu noklus\u0113si draudzen\u0113m,\nTu nosl\u0113psies aiz sl\u0113dzen\u0113m,\nTu drupsi, katru dienu drupsi.\n\nAr seju snieg\u0101.\nAr seju snieg\u0101. (2x)\n\nPiedz:\nS\u0101k p\u0101riet bailes,\nP\u0101riet bailes\nP\u0101riet bailes\nP\u0101riet Oohhoooo\n\n\nNav karma b\u0113bis nevar\u012bgs,\nT\u0101s kodiens esot ne\u017e\u0113l\u012bgs,\nPlus inde, n\u0101v\u0113jo\u0161a inde.\nK\u0101ds atraus m\u016bsu libido,\nAr spai\u0146iem \u0146ems un sasmels to.\nCik stulbi! Ak, cik tas ir stulbi!\n\nAr seju snieg\u0101.\nAr seju snieg\u0101. (x2)\n\nS\u0101k p\u0101riet bailes,\nP\u0101riet bailes... (x6)","bodyAbc":"","url":"\/song\/1676-Dons_Arturs_Singirejs_-_Pariet_Bailes","youtubeLink":"JksKO1C4x3g","updatedDate":"2022-03-13T18:39:07Z","createdDate":"2014-07-14T21:00:00Z","songTop":{"visitsWeekly":6},"mainArtist":{"id":69,"title":"Dons (Art\u016brs \u0160ingirejs)","url":"\/band\/69-Dons_Arturs_Singirejs","songCount":70,"updatedDate":"2023-07-05T20:41:09.035Z","createdDate":"2023-01-31T08:20:58.13Z"},"tags":[],"poets":[{"id":324,"title":"Ingus B\u0113rzi\u0146\u0161","url":"\/band\/324-Ingus_Berzins","songCount":11,"updatedDate":"2022-03-13T18:39:07Z","createdDate":"2019-01-28T08:09:29Z"}],"composers":[{"id":69,"title":"Dons (Art\u016brs \u0160ingirejs)","url":"\/band\/69-Dons_Arturs_Singirejs","songCount":70,"updatedDate":"2023-07-05T20:41:09.035Z","createdDate":"2023-01-31T08:20:58.13Z"}],"performers":[{"id":69,"title":"Dons (Art\u016brs \u0160ingirejs)","url":"\/band\/69-Dons_Arturs_Singirejs","songCount":70,"updatedDate":"2023-07-05T20:41:09.035Z","createdDate":"2023-01-31T08:20:58.13Z"}]}