{"id":328,"title":"Besame Mucho","body":"M\u016bzika: Consuelo Vel\u00e1zquez, 1940\r\n\r\nCm                     Fm\r\n\u0160\u0137iroties\u2026, br\u012bd\u012b tik skumj\u0101\u2026,\r\n Fm                            Cm\r\nMeitene m\u012b\u013cot\u0101 neat\u013cauj asar\u0101m pl\u016bst....\r\nC7                Fm\r\nBr\u012bd\u012b\u2026, br\u012bd\u012b tik skumj\u0101\u2026,\r\nCm                     D7       G7         Cm       C7\r\nPieglaudies maig\u0101k lai dedz\u012bg\u0101k kv\u0113lo tavs sk\u016bpsts.\r\n\r\nPiedz.:\r\nFm                      Cm                   G                  Cm C7\r\nNakts dr\u012bzi proj\u0101m ies, debesis zv\u012b\u013cot s\u0101ks, ausm\u0101 m\u016bs t\u0101le jau \u0161\u0137irs,\r\nFm                         Cm              D7                   G7\r\nSirds smeldz man \u0161\u0137iroties meitene m\u012b\u013cot\u0101, smagi, ka laime mums irst.\r\n\r\n\u0160\u0137iroties, skatien\u0101 zaig\u0101,\r\nP\u0113d\u0113jo reizi v\u0113l sirdi man sasild\u012bt \u013cauj.\r\nNevajag, nevajag raud\u0101t,\r\nPieglaudies maig\u0101k, v\u0113l dedz\u012bg\u0101k mani jel skauj.\r\n\r\nPiedz.: ,  Solo.\r\n\r\nSk\u016bpsti man', atkal man' sk\u016bpsti,\r\nM\u012bl\u0101, kad piek\u013caujos tev strauja pukst mana sirds.\r\nSk\u016bpsti man', atkal man' sk\u016bpsti,\r\nSauc mani m\u012b\u013c\u0101 un teic ka tu piederi man.\r\n\r\nPiedz:\r\n\u0160\u012b m\u012bla bij' kaisl\u012bga, stipra un varena, salauzt to nesp\u0113j nekas.\r\nKur\u0161 v\u0113l t\u0101 m\u012bl\u0113jis, uz tevi cer\u0113jis, sap\u0146ojis nakti un dien'.\r\n\r\nSolo:  (T\u0113ma)  izska\u0146a 2X.\r\n\r\n","bodyLyrics":"M\u016bzika: Consuelo Vel\u00e1zquez, 1940\n\n\u0160\u0137iroties\u2026, br\u012bd\u012b tik skumj\u0101\u2026,\nMeitene m\u012b\u013cot\u0101 neat\u013cauj asar\u0101m pl\u016bst....\nBr\u012bd\u012b\u2026, br\u012bd\u012b tik skumj\u0101\u2026,\nPieglaudies maig\u0101k lai dedz\u012bg\u0101k kv\u0113lo tavs sk\u016bpsts.\n\nPiedz.:\nNakts dr\u012bzi proj\u0101m ies, debesis zv\u012b\u013cot s\u0101ks, ausm\u0101 m\u016bs t\u0101le jau \u0161\u0137irs,\nSirds smeldz man \u0161\u0137iroties meitene m\u012b\u013cot\u0101, smagi, ka laime mums irst.\n\n\u0160\u0137iroties, skatien\u0101 zaig\u0101,\nP\u0113d\u0113jo reizi v\u0113l sirdi man sasild\u012bt \u013cauj.\nNevajag, nevajag raud\u0101t,\nPieglaudies maig\u0101k, v\u0113l dedz\u012bg\u0101k mani jel skauj.\n\nPiedz.: , Solo.\n\nSk\u016bpsti man', atkal man' sk\u016bpsti,\nM\u012bl\u0101, kad piek\u013caujos tev strauja pukst mana sirds.\nSk\u016bpsti man', atkal man' sk\u016bpsti,\nSauc mani m\u012b\u013c\u0101 un teic ka tu piederi man.\n\nPiedz:\n\u0160\u012b m\u012bla bij' kaisl\u012bga, stipra un varena, salauzt to nesp\u0113j nekas.\nKur\u0161 v\u0113l t\u0101 m\u012bl\u0113jis, uz tevi cer\u0113jis, sap\u0146ojis nakti un dien'.\n\nSolo: (T\u0113ma) izska\u0146a 2X.","bodyAbc":"","url":"\/song\/328-Andris_Danilenko_-_Besame_Mucho","youtubeLink":"","updatedDate":"2022-02-26T16:21:02Z","createdDate":"2007-03-21T22:00:00Z","songTop":{"visitsWeekly":0},"mainArtist":{"id":416,"title":"Andris Da\u0146i\u013cenko","url":"\/band\/416-Andris_Danilenko","songCount":9,"updatedDate":"2022-02-26T16:19:11Z","createdDate":"2014-08-13T21:00:00Z"},"tags":[],"poets":[],"composers":[],"performers":[{"id":416,"title":"Andris Da\u0146i\u013cenko","url":"\/band\/416-Andris_Danilenko","songCount":9,"updatedDate":"2022-02-26T16:19:11Z","createdDate":"2014-08-13T21:00:00Z"}]}