{"id":4121,"title":"Kom\u0113ta N\u0101k","body":"Es dzirdu baumas, ka b\u016bs dr\u012bz liels kar\u0161\nT\u0101 run\u0101 vai t\u0101 ir, par to tu str\u012bdies pats\nMan ir lietas j\u0101dara, bet man ir m\u012bziens mazs\nUn jut\u012b\u0161os stulbi, ja notiks r\u012btdien tas\nEs dzird\u0113ju, ka s\u0101k pr\u0101t\u012bgie just\nKa dr\u012bz main\u012bsies viss, un \u0161\u012b k\u0101rt\u012bba bruks\nUn ka neb\u016bs no t\u0101 visa gl\u0101bi\u0146a mums\nUn viss ir bezcer\u012bg\u0101k, nek\u0101 b\u0101re\u0146u skumjas\nEs dzird\u0113ju, k\u0101 pare\u0123o let\u0101lus s\u016bdus\nP\u0113c p\u0101ris gadiem \u0161\u012b plan\u0113ta nepavilks m\u016bs\nDzird\u0113ju no kol\u0113\u0123a k\u0101da\nKa pasaule beigsies, ka kom\u0113ta n\u0101k\nBet tas nekad nenotiek, k\u0101 Vener\u0101 ziemas\nK\u0101p\u0113c visi gaida p\u0113d\u0113j\u0101s dienas?\nK\u0101, to visu zinot, gul\u0113t vari dienas gal\u0101?\nUn ja tu tam tici, ko tu dari lietas lab\u0101?\n \nPiedz.\n21. gadsimts \u2013 tas ir roks un plastmasa\n\u201eRepublika\u201d tikai v\u0101rds ir, un Tavs boss ir patva\u013ca\nYoutub\u0101 br\u012bnumus redz, k\u0101 kross l\u012bdz Maskavai,\nGaja Foksa maskas, k\u0101j\u0101s botas ne pastalas\nSola pasaules galu, ka b\u016bsim pekl\u0113 pat\nMaiju kalend\u0101rs panes\u0101s, ir pat pres\u0113 tas\nEs gaidu, lai redz\u0113tu, vai tas mani nesp\u0113s skart\nBet, ja pasaule nebeigsies, j\u0101s\u0101k mekl\u0113t darbs\n \nKas no t\u0101 visa \u012bsts ir, es ne\u0146emos der\u0113t\nMan draugs teica, ka vi\u0146\u0161 NLO redz\u0113ja\nEs b\u0113ni\u0146os, kur lietas nez cik uzkr\u0101tas\nDzird\u0113ju so\u013cus, bet tur neviens neuztur\u0101s\nRun\u0101, esi mu\u013c\u0137is, ja uz konstit\u016bciju tu ceri\nKaut kur izlas\u012bju, ka evol\u016bcija ir meli\nK\u0101ds teica, ka zi\u0146as ir tikai lieliska diversija\nRedz\u0113ju youtub\u0101, ka ir vienpadsmit dimensijas\nKaut kur sugas izmirst \u2013 panik\u0101 skandina\nBet nekad dz\u012bve neredz\u0113ju vali vai pandu\nKad p\u0113t\u012bjumus zin\u0101tnieki cit\u0113 un r\u0101da\nAtliek t\u0101dam k\u0101 man te tikai tic\u0113t uz v\u0101rda\nNets ar zino\u0161ajiem bariem pilns\nKuri run\u0101s, bet dar\u012b\u0161anu gadiem vilks\nJa nav bunkura, k\u0101 pal\u012bdz\u0113s tev paties\u0101s filmas\nB\u016bsi starp tiem, kurus noslauc\u012bs spr\u0101dziena vilnis\nNezinu, vai ilgi m\u016bsu plan\u0113ta v\u0113l b\u016bs\nVai tie\u0161i mani film\u0113 kamera uz st\u016bra\nVai ar\u012b caur interneta kabeli es s\u016btu\nDatus par to, ko lasu vai paral\u0113li l\u016bru\nMan neprasi par varu, kas c\u012bn\u0101s\nEs liel\u0101ko da\u013cu gada pavadu R\u012bg\u0101\nJa prasi, k\u0101das nelaimes var uzklupt v\u0113l\nEs nezinu, bet es to varu uzgugl\u0113t\n \nPiedz. 2X","bodyLyrics":"Es dzirdu baumas, ka b\u016bs dr\u012bz liels kar\u0161\nT\u0101 run\u0101 vai t\u0101 ir, par to tu str\u012bdies pats\nMan ir lietas j\u0101dara, bet man ir m\u012bziens mazs\nUn jut\u012b\u0161os stulbi, ja notiks r\u012btdien tas\nEs dzird\u0113ju, ka s\u0101k pr\u0101t\u012bgie just\nKa dr\u012bz main\u012bsies viss, un \u0161\u012b k\u0101rt\u012bba bruks\nUn ka neb\u016bs no t\u0101 visa gl\u0101bi\u0146a mums\nUn viss ir bezcer\u012bg\u0101k, nek\u0101 b\u0101re\u0146u skumjas\nEs dzird\u0113ju, k\u0101 pare\u0123o let\u0101lus s\u016bdus\nP\u0113c p\u0101ris gadiem \u0161\u012b plan\u0113ta nepavilks m\u016bs\nDzird\u0113ju no kol\u0113\u0123a k\u0101da\nKa pasaule beigsies, ka kom\u0113ta n\u0101k\nBet tas nekad nenotiek, k\u0101 Vener\u0101 ziemas\nK\u0101p\u0113c visi gaida p\u0113d\u0113j\u0101s dienas?\nK\u0101, to visu zinot, gul\u0113t vari dienas gal\u0101?\nUn ja tu tam tici, ko tu dari lietas lab\u0101?\n\nPiedz.\n21. gadsimts \u2013 tas ir roks un plastmasa\n\u201eRepublika\u201d tikai v\u0101rds ir, un Tavs boss ir patva\u013ca\nYoutub\u0101 br\u012bnumus redz, k\u0101 kross l\u012bdz Maskavai,\nGaja Foksa maskas, k\u0101j\u0101s botas ne pastalas\nSola pasaules galu, ka b\u016bsim pekl\u0113 pat\nMaiju kalend\u0101rs panes\u0101s, ir pat pres\u0113 tas\nEs gaidu, lai redz\u0113tu, vai tas mani nesp\u0113s skart\nBet, ja pasaule nebeigsies, j\u0101s\u0101k mekl\u0113t darbs\n\nKas no t\u0101 visa \u012bsts ir, es ne\u0146emos der\u0113t\nMan draugs teica, ka vi\u0146\u0161 NLO redz\u0113ja\nEs b\u0113ni\u0146os, kur lietas nez cik uzkr\u0101tas\nDzird\u0113ju so\u013cus, bet tur neviens neuztur\u0101s\nRun\u0101, esi mu\u013c\u0137is, ja uz konstit\u016bciju tu ceri\nKaut kur izlas\u012bju, ka evol\u016bcija ir meli\nK\u0101ds teica, ka zi\u0146as ir tikai lieliska diversija\nRedz\u0113ju youtub\u0101, ka ir vienpadsmit dimensijas\nKaut kur sugas izmirst \u2013 panik\u0101 skandina\nBet nekad dz\u012bve neredz\u0113ju vali vai pandu\nKad p\u0113t\u012bjumus zin\u0101tnieki cit\u0113 un r\u0101da\nAtliek t\u0101dam k\u0101 man te tikai tic\u0113t uz v\u0101rda\nNets ar zino\u0161ajiem bariem pilns\nKuri run\u0101s, bet dar\u012b\u0161anu gadiem vilks\nJa nav bunkura, k\u0101 pal\u012bdz\u0113s tev paties\u0101s filmas\nB\u016bsi starp tiem, kurus noslauc\u012bs spr\u0101dziena vilnis\nNezinu, vai ilgi m\u016bsu plan\u0113ta v\u0113l b\u016bs\nVai tie\u0161i mani film\u0113 kamera uz st\u016bra\nVai ar\u012b caur interneta kabeli es s\u016btu\nDatus par to, ko lasu vai paral\u0113li l\u016bru\nMan neprasi par varu, kas c\u012bn\u0101s\nEs liel\u0101ko da\u013cu gada pavadu R\u012bg\u0101\nJa prasi, k\u0101das nelaimes var uzklupt v\u0113l\nEs nezinu, bet es to varu uzgugl\u0113t\n\nPiedz. 2X","bodyAbc":"","url":"\/song\/4121-Edavardi_-_Kometa_Nak","youtubeLink":"","updatedDate":"2022-02-26T16:21:25Z","createdDate":"2020-06-03T20:35:40Z","songTop":{"visitsWeekly":0},"mainArtist":{"id":1146,"title":"Edav\u0101rdi","url":"\/band\/1146-Edavardi","songCount":27,"updatedDate":"2023-03-05T20:14:08.446Z","createdDate":"2018-01-21T08:07:21Z"},"tags":[{"id":22,"title":"bez akordiem","url":"\/tag\/22-Bez_Akordiem","songCount":1535,"labelColor":"#95a5a6"}],"poets":[{"id":1146,"title":"Edav\u0101rdi","url":"\/band\/1146-Edavardi","songCount":27,"updatedDate":"2023-03-05T20:14:08.446Z","createdDate":"2018-01-21T08:07:21Z"}],"composers":[{"id":1263,"title":"ansis","url":"\/band\/1263-Ansis","songCount":7,"updatedDate":"2022-02-26T16:19:11Z","createdDate":"2019-02-12T20:27:52Z"}],"performers":[{"id":1146,"title":"Edav\u0101rdi","url":"\/band\/1146-Edavardi","songCount":27,"updatedDate":"2023-03-05T20:14:08.446Z","createdDate":"2018-01-21T08:07:21Z"}]}