{"id":2495,"title":"Siksp\u0101r\u0146a Fledermau\u0161a \u0160\u016bpu\u013cdziesma","body":"[C] B\u0113ni\u0146os, kur tum\u0161s k\u0101 pekl\u0113,\r\nLaiks tek gausi, gausi.\r\n[C] Sald\u0101 mieg\u0101, [G] k\u0101j\u0101m gais\u0101\r\n[F] Guli, Fleder[C]mausi!\r\n\r\n[C] Tumsa z\u012bdaina un m\u012bksta,\r\nNakts no za\u013ca pl\u012b\u0161a,\r\n[C] Savos sp\u0101rnos [G] ietinieties,\r\n[F] Mefistofe[C]l\u012b\u0161i!\r\n\r\n[Am] B\u0113ni\u0146os, kur tum\u0161s k\u0101 [F] pekl\u0113,\r\nDz\u012bvo za\u013ci velni.\r\n[Am] B\u0113ni\u0146os, kur tum\u0161s k\u0101 [F] pekl\u0113,\r\nDz\u012bvo za\u013ci velni.\r\n[Am] Sald\u0101 mieg\u0101, k\u0101j\u0101m [F] gais\u0101\r\nDz\u012bvo za\u013ci velni.\r\n[G] Sapn\u012b silti, silti pelni.\r\n\r\n[C] Mums ir nakts, m\u0113s neat\u013causim\r\nGaismai pie mums ien\u0101kt.\r\n[C] Gar\u0101m s\u0101rt\u0101m [G] st\u0101r\u0137a k\u0101j\u0101m\r\n[F] Lauk\u0101 so\u013co [C] diena.\r\n\r\n[C] Satinieties, aptinieties,\r\nAizkor\u0137\u0113jiet ausis! \r\n[C] Sald\u0101 mieg\u0101, [G] k\u0101j\u0101m gais\u0101\r\n[F] Guli, Fleder[C]mausi!\r\n\r\n  Guli, [C] guli \u2013 guli, guli\r\n  Fledermausi - Fledermausi\r\n  Sald\u0101 mieg\u0101 \u2013 sald\u0101 mieg\u0101\r\n  K\u0101j\u0101m gais\u0101 \u2013 k\u0101j\u0101m gais\u0101\r\n\r\n  Guli, [F] guli \u2013 guli, guli\r\n  Fledermausi - Fledermausi\r\n  Sald\u0101 [C] mieg\u0101 \u2013 sald\u0101 mieg\u0101\r\n  K\u0101j\u0101m gais\u0101 \u2013 k\u0101j\u0101m gais\u0101\r\n\r\n  Guli, [G] guli \u2013 guli, guli\r\n  Fledermausi - Fledermausi\r\n  Sald\u0101 [C] mieg\u0101\r\n  K\u0101j\u0101m gais\u0101\r\n\r\n[C] Mums ir nakts, m\u0113s neat\u013causim\r\nGaismai pie mums ien\u0101kt.\r\n[C] Gar\u0101m s\u0101rt\u0101m [G] st\u0101r\u0137a k\u0101j\u0101m\r\n[F] Lauk\u0101 so\u013co [C] diena.\r\n\r\n[C] Satinieties, aptinieties,\r\nAizkor\u0137\u0113jiet ausis! \r\n[C] Sald\u0101 mieg\u0101, [G] k\u0101j\u0101m gais\u0101\r\n[F] Guli, Fleder[C] mausi!\r\n\r\n  Guli, [C] guli \u2013 guli, guli\r\n  Fledermausi - Fledermausi\r\n  Sald\u0101 mieg\u0101 \u2013 sald\u0101 mieg\u0101\r\n  K\u0101j\u0101m gais\u0101 \u2013 k\u0101j\u0101m gais\u0101\r\n\r\n  Guli, [F] guli \u2013 guli, guli\r\n  Fledermausi - Fledermausi\r\n  Sald\u0101 [C] mieg\u0101 \u2013 sald\u0101 mieg\u0101\r\n  K\u0101j\u0101m gais\u0101 \u2013 k\u0101j\u0101m gais\u0101\r\n\r\n  Guli, [G] guli \u2013 guli, guli\r\n  Fledermausi - Fledermausi\r\n  Sald\u0101 [C] mieg\u0101\r\n  K\u0101j\u0101m gais\u0101","bodyLyrics":"B\u0113ni\u0146os, kur tum\u0161s k\u0101 pekl\u0113,\nLaiks tek gausi, gausi.\nSald\u0101 mieg\u0101, k\u0101j\u0101m gais\u0101\nGuli, Fledermausi!\n\nTumsa z\u012bdaina un m\u012bksta,\nNakts no za\u013ca pl\u012b\u0161a,\nSavos sp\u0101rnos ietinieties,\nMefistofel\u012b\u0161i!\n\nB\u0113ni\u0146os, kur tum\u0161s k\u0101 pekl\u0113,\nDz\u012bvo za\u013ci velni.\nB\u0113ni\u0146os, kur tum\u0161s k\u0101 pekl\u0113,\nDz\u012bvo za\u013ci velni.\nSald\u0101 mieg\u0101, k\u0101j\u0101m gais\u0101\nDz\u012bvo za\u013ci velni.\nSapn\u012b silti, silti pelni.\n\nMums ir nakts, m\u0113s neat\u013causim\nGaismai pie mums ien\u0101kt.\nGar\u0101m s\u0101rt\u0101m st\u0101r\u0137a k\u0101j\u0101m\nLauk\u0101 so\u013co diena.\n\nSatinieties, aptinieties,\nAizkor\u0137\u0113jiet ausis! \nSald\u0101 mieg\u0101, k\u0101j\u0101m gais\u0101\nGuli, Fledermausi!\n\nGuli, guli \u2013 guli, guli\nFledermausi - Fledermausi\nSald\u0101 mieg\u0101 \u2013 sald\u0101 mieg\u0101\nK\u0101j\u0101m gais\u0101 \u2013 k\u0101j\u0101m gais\u0101\n\nGuli, guli \u2013 guli, guli\nFledermausi - Fledermausi\nSald\u0101 mieg\u0101 \u2013 sald\u0101 mieg\u0101\nK\u0101j\u0101m gais\u0101 \u2013 k\u0101j\u0101m gais\u0101\n\nGuli, guli \u2013 guli, guli\nFledermausi - Fledermausi\nSald\u0101 mieg\u0101\nK\u0101j\u0101m gais\u0101\n\nMums ir nakts, m\u0113s neat\u013causim\nGaismai pie mums ien\u0101kt.\nGar\u0101m s\u0101rt\u0101m st\u0101r\u0137a k\u0101j\u0101m\nLauk\u0101 so\u013co diena.\n\nSatinieties, aptinieties,\nAizkor\u0137\u0113jiet ausis! \nSald\u0101 mieg\u0101, k\u0101j\u0101m gais\u0101\nGuli, Fleder mausi!\n\nGuli, guli \u2013 guli, guli\nFledermausi - Fledermausi\nSald\u0101 mieg\u0101 \u2013 sald\u0101 mieg\u0101\nK\u0101j\u0101m gais\u0101 \u2013 k\u0101j\u0101m gais\u0101\n\nGuli, guli \u2013 guli, guli\nFledermausi - Fledermausi\nSald\u0101 mieg\u0101 \u2013 sald\u0101 mieg\u0101\nK\u0101j\u0101m gais\u0101 \u2013 k\u0101j\u0101m gais\u0101\n\nGuli, guli \u2013 guli, guli\nFledermausi - Fledermausi\nSald\u0101 mieg\u0101\nK\u0101j\u0101m gais\u0101","bodyAbc":"","url":"\/song\/2495-Cosmos_-_Siksparna_Fledermausa_Supuldziesma","youtubeLink":"ymGryF6DZWI","updatedDate":"2022-02-26T16:21:14Z","createdDate":"2016-02-08T08:27:26Z","songTop":{"visitsWeekly":3},"mainArtist":{"id":88,"title":"Cosmos","url":"\/band\/88-Cosmos","songCount":13,"updatedDate":"2022-02-26T16:19:11Z","createdDate":"2007-12-17T22:00:00Z"},"tags":[],"poets":[{"id":640,"title":"Dagnija Dreika-Matule","url":"\/band\/640-Dagnija_Dreika-Matule","songCount":9,"updatedDate":"2022-02-26T16:19:11Z","createdDate":"2015-07-10T10:07:10Z"}],"composers":[{"id":4,"title":"Raimonds Pauls","url":"\/band\/4-Raimonds_Pauls","songCount":252,"updatedDate":"2023-11-15T11:11:02.02Z","createdDate":"2022-10-22T17:39:34Z"}],"performers":[{"id":88,"title":"Cosmos","url":"\/band\/88-Cosmos","songCount":13,"updatedDate":"2022-02-26T16:19:11Z","createdDate":"2007-12-17T22:00:00Z"},{"id":192,"title":"Viktors Lap\u010denoks","url":"\/band\/192-Viktors_Lapcenoks","songCount":46,"updatedDate":"2023-10-23T12:06:39.423Z","createdDate":"2009-10-11T21:00:00Z"},{"id":305,"title":"Nora Bumbiere","url":"\/band\/305-Nora_Bumbiere","songCount":44,"updatedDate":"2023-01-15T18:24:50.128Z","createdDate":"2022-10-20T11:42:44Z"}]}