{"id":1965,"title":"Sniegav\u012brs","body":"D\r\nBriljanti, kas rot\u0101jas\r\n   A\r\nUz m\u0101ju jumtiem, pagalmos,\r\n    Bm\r\nKas kr\u012bt, no gaisa kr\u012bt.\r\n    D\r\nRe, sniegav\u012brs uz ielas \u0161\u012bs\r\nA                                 Bm\r\nVien\u012bgais tik balts, tik balts un t\u012brs,\r\n\r\nTik balts un t\u012brs.\r\n\r\n    D                A\r\nVakaros, kad satumst viss,\r\n          D           A   \r\nTik sniegav\u012brs ir palicis\r\n         D              A\r\nuz ielas \u0161\u012bs, kur br\u012bnumi\r\n        Bm\r\nk\u0101 sald\u0113jums uz m\u0113les k\u016bst.\r\n\r\nD                  \r\nSniegav\u012brs ir ap\u0146\u0113m\u012bgs\r\n   A\r\nAr visiem laimi dal\u012bt\r\n    Bm\r\nTas prot, ja citi rod\r\nD\r\nZiemas priekos dal\u012bties,\r\nA                    Bm      \r\nPasaku st\u0101stos klaus\u012bties un nenob\u012bties.\r\n\r\n    D                A\r\nVakaros, kad satumst viss,\r\n          D           A   \r\nTik sniegav\u012brs ir palicis\r\n         D              A\r\nuz ielas \u0161\u012bs, kur br\u012bnumi\r\n        Bm\r\nk\u0101 sald\u0113jums uz m\u0113les k\u016bst.\r\n\r\nSv\u0113tku smar\u017eas vis, visapk\u0101rt kl\u012bst,\r\nkas atn\u0101ks pirmais tas, tas ieraudz\u012bs,\r\ncik gai\u0161a nakts p\u0101r zemi \u0161o,\r\ncik gai\u0161a nakts p\u0101r zemi..\r\n\r\nVakaros, kad viss\r\nmiers uz zemi nolaidies\r\nEj uz ielas \u0161\u012bs, kur br\u012bnumi k\u0101 sald\u0113jums uz m\u0113les k\u016bst, uz m\u0113les k\u016bst, uz m\u0113les k\u016bst...k\u016bst.\r\n","bodyLyrics":"Briljanti, kas rot\u0101jas\nUz m\u0101ju jumtiem, pagalmos,\nKas kr\u012bt, no gaisa kr\u012bt.\nRe, sniegav\u012brs uz ielas \u0161\u012bs\nVien\u012bgais tik balts, tik balts un t\u012brs,\n\nTik balts un t\u012brs.\n\nVakaros, kad satumst viss,\nTik sniegav\u012brs ir palicis\nuz ielas \u0161\u012bs, kur br\u012bnumi\nk\u0101 sald\u0113jums uz m\u0113les k\u016bst.\n\nSniegav\u012brs ir ap\u0146\u0113m\u012bgs\nAr visiem laimi dal\u012bt\nTas prot, ja citi rod\nZiemas priekos dal\u012bties,\nPasaku st\u0101stos klaus\u012bties un nenob\u012bties.\n\nVakaros, kad satumst viss,\nTik sniegav\u012brs ir palicis\nuz ielas \u0161\u012bs, kur br\u012bnumi\nk\u0101 sald\u0113jums uz m\u0113les k\u016bst.\n\nSv\u0113tku smar\u017eas vis, visapk\u0101rt kl\u012bst,\nkas atn\u0101ks pirmais tas, tas ieraudz\u012bs,\ncik gai\u0161a nakts p\u0101r zemi \u0161o,\ncik gai\u0161a nakts p\u0101r zemi..\n\nVakaros, kad viss\nmiers uz zemi nolaidies\nEj uz ielas \u0161\u012bs, kur br\u012bnumi k\u0101 sald\u0113jums uz m\u0113les k\u016bst, uz m\u0113les k\u016bst, uz m\u0113les k\u016bst...k\u016bst.","bodyAbc":"","url":"\/song\/1965-Double_Faced_Eels_-_Sniegavirs","youtubeLink":"lMVPQzq7MdA","updatedDate":"2022-02-26T16:21:10Z","createdDate":"2014-12-14T17:28:09Z","songTop":{"visitsWeekly":0},"mainArtist":{"id":40,"title":"Double Faced Eels","url":"\/band\/40-Double_Faced_Eels","songCount":21,"updatedDate":"2023-03-13T06:40:06.271Z","createdDate":"2023-01-24T09:51:51.09Z"},"tags":[{"id":4,"title":"ziemassv\u0113tku","url":"\/tag\/4-Ziemassvetku","songCount":80,"labelColor":"#3498db"}],"poets":[],"composers":[],"performers":[{"id":40,"title":"Double Faced Eels","url":"\/band\/40-Double_Faced_Eels","songCount":21,"updatedDate":"2023-03-13T06:40:06.271Z","createdDate":"2023-01-24T09:51:51.09Z"}]}