{"id":2709,"title":"Visi ziedi izzied\u0113ja","body":"","bodyLyrics":"","bodyAbc":"","url":"\/song\/2709-Ilgi_-_Visi_Ziedi_Izziedeja","youtubeLink":"9zJSNwrfqD8","updatedDate":"2022-02-26T16:21:15Z","createdDate":"2016-06-21T10:03:28Z","songTop":{"visitsWeekly":1},"mainArtist":{"id":408,"title":"I\u013c\u0123i","url":"\/band\/408-Ilgi","songCount":10,"updatedDate":"2022-11-08T13:46:45Z","createdDate":"2022-11-08T13:46:45Z"},"tags":[{"id":5,"title":"l\u012bgo","url":"\/tag\/5-Ligo","songCount":12,"labelColor":"#00bd06"}],"poets":null,"composers":null,"performers":null}