{"id":288,"title":"Gula meit\u012bna","body":"C       G    Am         Em\r\nGula meit\u012bna l\u012bdz brokast\u012bnu,\r\nC        G   C  G\r\nPuis\u012btis netic\u0113ja\r\nC          G    Am       Em\r\nCelies meit\u012bna, mana sirsn\u012bna,\r\nF          G     C\r\nVai v\u0113l tu neizgul\u0113j?\r\n\r\nGula meit\u012bna l\u012bdz launadz\u012bnu,\r\nPuis\u012btis netic\u0113ja\r\nCelies meit\u012bna, mana sirsn\u012bna,\r\nVai v\u0113l tu neizgul\u0113j?\r\n\r\nGula meit\u012bna l\u012bdz vakar\u012bnu,\r\nPuis\u012btis netic\u0113ja\r\nCelies meit\u012bna, mana sirsn\u012bna,\r\nVai v\u0113l tu neizgul\u0113j?\r\n\r\nMeit\u012bnu lika iek\u0161 balta z\u0101rka,\r\nPuis\u012btis netic\u0113ja.\r\nCelies meit\u012bna, mana sirsn\u012bna,\r\nVai v\u0113l tu neizgul\u0113j?\r\n\r\nMeit\u012bnu laida iek\u0161 dzi\u013cas bedres,\r\nPuis\u012btis netic\u0113ja.\r\nCelies meit\u012bna, mana sirsn\u012bna,\r\nVai v\u0113l tu neizgul\u0113j?\r\n\r\nMeit\u012bnu b\u0113ra ar balt\u0101m smilt\u012bm,\r\nS\u0101k puis\u012bts gau\u017ei raud\u0101t.\r\nJemiet zobenu, c\u0113rtiet galv\u0113nu,\r\nLaidiet ir mani l\u012bdz.","bodyLyrics":"Gula meit\u012bna l\u012bdz brokast\u012bnu,\nPuis\u012btis netic\u0113ja\nCelies meit\u012bna, mana sirsn\u012bna,\nVai v\u0113l tu neizgul\u0113j?\n\nGula meit\u012bna l\u012bdz launadz\u012bnu,\nPuis\u012btis netic\u0113ja\nCelies meit\u012bna, mana sirsn\u012bna,\nVai v\u0113l tu neizgul\u0113j?\n\nGula meit\u012bna l\u012bdz vakar\u012bnu,\nPuis\u012btis netic\u0113ja\nCelies meit\u012bna, mana sirsn\u012bna,\nVai v\u0113l tu neizgul\u0113j?\n\nMeit\u012bnu lika iek\u0161 balta z\u0101rka,\nPuis\u012btis netic\u0113ja.\nCelies meit\u012bna, mana sirsn\u012bna,\nVai v\u0113l tu neizgul\u0113j?\n\nMeit\u012bnu laida iek\u0161 dzi\u013cas bedres,\nPuis\u012btis netic\u0113ja.\nCelies meit\u012bna, mana sirsn\u012bna,\nVai v\u0113l tu neizgul\u0113j?\n\nMeit\u012bnu b\u0113ra ar balt\u0101m smilt\u012bm,\nS\u0101k puis\u012bts gau\u017ei raud\u0101t.\nJemiet zobenu, c\u0113rtiet galv\u0113nu,\nLaidiet ir mani l\u012bdz.","bodyAbc":"","url":"\/song\/288-Latviesu_Tautasdziesma_-_Gula_Meitina","youtubeLink":"","updatedDate":"2024-03-17T01:42:47.577361Z","createdDate":"2007-03-07T22:00:00Z","songTop":{"visitsWeekly":2},"mainArtist":{"id":55,"title":"Latvie\u0161u tautasdziesma","url":"\/band\/55-Latviesu_Tautasdziesma","songCount":170,"updatedDate":"2023-11-07T07:17:01.148Z","createdDate":"2023-01-12T21:26:56.606Z"},"tags":[],"poets":[],"composers":[],"performers":[{"id":55,"title":"Latvie\u0161u tautasdziesma","url":"\/band\/55-Latviesu_Tautasdziesma","songCount":170,"updatedDate":"2023-11-07T07:17:01.148Z","createdDate":"2023-01-12T21:26:56.606Z"}]}