{"id":2193,"title":"R\u016btoj","body":"","bodyLyrics":"","bodyAbc":"","url":"\/song\/2193-Lana_Franceska_-_Rutoj","youtubeLink":"KOsFSj0rW18","updatedDate":"2023-08-24T08:36:35.701Z","createdDate":"2015-06-29T08:38:05Z","songTop":{"visitsWeekly":0},"mainArtist":{"id":615,"title":"Lana Fran\u010deska","url":"\/band\/615-Lana_Franceska","songCount":7,"updatedDate":"2023-08-24T08:36:42.641Z","createdDate":"2015-06-29T08:38:05Z"},"tags":[{"id":5,"title":"l\u012bgo","url":"\/tag\/5-Ligo","songCount":12,"labelColor":"#00bd06"},{"id":19,"title":"latgaliski","url":"\/tag\/19-Latgaliski","songCount":117,"labelColor":"#18bc9c"}],"poets":null,"composers":null,"performers":null}