{"id":2959,"title":"K\u0101dai mei\u010dai Cesvain\u0113","body":"Gai\u0161os ziedus vasara v\u0113jos ieb\u016brusi,\r\nLai tie visi \u0161\u016bpotos tik uz tavu pusi.\r\nK\u0101dreiz teici s\u016brum\u0101: gundegai es rada,\r\nNu varb\u016bt tak maigums r\u0101ms mani \u0161odien vada.\r\n\r\n  K\u0101dai mei\u010dai Cesvain\u0113 es \u0161\u012bs rindas rakstu,\r\n  Jo man gr\u016bti vakaros v\u0113rt aiz laimes plakstu.\r\n  Sen varb\u016bt t\u0101 aizg\u0101jusi prom pa sve\u0161u taku,\r\n  Tom\u0113r dom\u0101s at\u013caus man paiet br\u012bdi blakus.\r\n\r\nManu sap\u0146u pl\u012bvur\u012b iesl\u0113dz eg\u013cu sienas,\r\nT\u0101lu pla\u0161\u0101 lei\u0161mal\u0113 vadu savas dienas.\r\nReiz\u0113m ilgi vakaros raugos es pret rietu,\r\nDebess pus\u0113 mekl\u0113jot tavu dz\u012bves vietu.\r\n\r\n  Zini, meit\u0113n, au\u0161\u012bg\u0101, ja tu k\u0101dreiz n\u0101ksi\r\n  \u0160urp, uz t\u0101lo lei\u0161mali, pabeigt sapni savu,\r\n  Es tev teik\u0161u klusi\u0146\u0101m, t\u0101, ka tikko dzirdi:\r\n  Var pat s\u016brai gundegai m\u012bla noburt sirdi.","bodyLyrics":"Gai\u0161os ziedus vasara v\u0113jos ieb\u016brusi,\nLai tie visi \u0161\u016bpotos tik uz tavu pusi.\nK\u0101dreiz teici s\u016brum\u0101: gundegai es rada,\nNu varb\u016bt tak maigums r\u0101ms mani \u0161odien vada.\n\nK\u0101dai mei\u010dai Cesvain\u0113 es \u0161\u012bs rindas rakstu,\nJo man gr\u016bti vakaros v\u0113rt aiz laimes plakstu.\nSen varb\u016bt t\u0101 aizg\u0101jusi prom pa sve\u0161u taku,\nTom\u0113r dom\u0101s at\u013caus man paiet br\u012bdi blakus.\n\nManu sap\u0146u pl\u012bvur\u012b iesl\u0113dz eg\u013cu sienas,\nT\u0101lu pla\u0161\u0101 lei\u0161mal\u0113 vadu savas dienas.\nReiz\u0113m ilgi vakaros raugos es pret rietu,\nDebess pus\u0113 mekl\u0113jot tavu dz\u012bves vietu.\n\nZini, meit\u0113n, au\u0161\u012bg\u0101, ja tu k\u0101dreiz n\u0101ksi\n\u0160urp, uz t\u0101lo lei\u0161mali, pabeigt sapni savu,\nEs tev teik\u0161u klusi\u0146\u0101m, t\u0101, ka tikko dzirdi:\nVar pat s\u016brai gundegai m\u012bla noburt sirdi.","bodyAbc":"","url":"\/song\/2959-Viktors_Lapcenoks_-_Kadai_Meicai_Cesvaine","youtubeLink":"RCT6DusHa8c","updatedDate":"2022-02-26T16:21:17Z","createdDate":"2017-06-03T09:58:32Z","songTop":{"visitsWeekly":0},"mainArtist":{"id":192,"title":"Viktors Lap\u010denoks","url":"\/band\/192-Viktors_Lapcenoks","songCount":46,"updatedDate":"2023-10-23T12:06:39.423Z","createdDate":"2009-10-11T21:00:00Z"},"tags":[{"id":22,"title":"bez akordiem","url":"\/tag\/22-Bez_Akordiem","songCount":1535,"labelColor":"#95a5a6"}],"poets":[{"id":864,"title":"Andrejs Balodis","url":"\/band\/864-Andrejs_Balodis","songCount":2,"updatedDate":"2022-02-26T16:19:11Z","createdDate":"2016-06-28T20:28:11Z"}],"composers":[{"id":291,"title":"Eduards Rozen\u0161trauhs","url":"\/band\/291-Eduards_Rozenstrauhs","songCount":13,"updatedDate":"2023-02-20T11:55:54.415Z","createdDate":"2014-07-10T21:00:00Z"}],"performers":[{"id":192,"title":"Viktors Lap\u010denoks","url":"\/band\/192-Viktors_Lapcenoks","songCount":46,"updatedDate":"2023-10-23T12:06:39.423Z","createdDate":"2009-10-11T21:00:00Z"}]}