{"id":3020,"title":"Glezna","body":"C G C G\r\nC        G        Am       G    C\r\n\u0145em\u0161u es kr\u0101su un glezno\u0161u saulrietu\r\nC        G             Am        G C\r\nTik siltu un maigu k\u0101 sv\u0113tdienas r\u012btu\r\nAm G Dm\r\nC          G\r\nkur liksim zvaigznes \r\n        Am           G  C\r\nkur t\u0101s s\u0113sim priek\u0161 laimes\r\n   C     G               Am     G  C\r\nto piena ce\u013cu lab\u0101k tav\u0101 kafij\u0101 leju\r\nAm G Dm\r\nAm G Dm\r\n\r\nPiedz.\r\nDm         C\r\npasaki man kur esi tu\r\nF         \r\ntur starp putniem\r\nBb\r\ntur starp zvaigzn\u0113m\r\nDm         C\r\npasaki man kur esmu es\r\nF\r\ntur kur kr\u0101sas\r\nBb\r\np\u0101rtop saul\u0113\r\n\r\nC        G            Am     G    C\r\nTur \u0161alc j\u016bra un mums aus\u012bs \u010dukst t\u0101\r\nC              G\r\nPar p\u0113d\u0101m,kas iem\u012btas\r\nAm        G      C\r\naizved t\u0101l\u0101 m\u016b\u017e\u012bb\u0101\r\n\r\nPiedz.\r\nDm         C\r\npasaki man kur esi tu\r\nF         \r\ntur starp putniem\r\nBb\r\ntur starp zvaigzn\u0113m\r\nDm         C\r\npasaki man kur esmu es\r\nF\r\ntur kur kr\u0101sas\r\nBb\r\np\u0101rtop saul\u0113","bodyLyrics":"\u0145em\u0161u es kr\u0101su un glezno\u0161u saulrietu\nTik siltu un maigu k\u0101 sv\u0113tdienas r\u012btu\nkur liksim zvaigznes \nkur t\u0101s s\u0113sim priek\u0161 laimes\nto piena ce\u013cu lab\u0101k tav\u0101 kafij\u0101 leju\n\nPiedz.\npasaki man kur esi tu\ntur starp putniem\ntur starp zvaigzn\u0113m\npasaki man kur esmu es\ntur kur kr\u0101sas\np\u0101rtop saul\u0113\n\nTur \u0161alc j\u016bra un mums aus\u012bs \u010dukst t\u0101\nPar p\u0113d\u0101m,kas iem\u012btas\naizved t\u0101l\u0101 m\u016b\u017e\u012bb\u0101\n\nPiedz.\npasaki man kur esi tu\ntur starp putniem\ntur starp zvaigzn\u0113m\npasaki man kur esmu es\ntur kur kr\u0101sas\np\u0101rtop saul\u0113","bodyAbc":"","url":"\/song\/3020-Cetri_Viena_-_Glezna","youtubeLink":"OVff7Z07GTM","updatedDate":"2022-02-26T16:21:17Z","createdDate":"2017-07-27T06:49:24Z","songTop":{"visitsWeekly":0},"mainArtist":{"id":1012,"title":"\u010cetri vien\u0101","url":"\/band\/1012-Cetri_Viena","songCount":2,"updatedDate":"2022-02-26T16:19:11Z","createdDate":"2017-07-27T06:49:24Z"},"tags":[],"poets":[{"id":1013,"title":"Ilze Rijniece","url":"\/band\/1013-Ilze_Rijniece","songCount":2,"updatedDate":"2022-02-26T16:19:11Z","createdDate":"2017-07-27T06:50:35Z"}],"composers":[{"id":1013,"title":"Ilze Rijniece","url":"\/band\/1013-Ilze_Rijniece","songCount":2,"updatedDate":"2022-02-26T16:19:11Z","createdDate":"2017-07-27T06:50:35Z"}],"performers":[{"id":1012,"title":"\u010cetri vien\u0101","url":"\/band\/1012-Cetri_Viena","songCount":2,"updatedDate":"2022-02-26T16:19:11Z","createdDate":"2017-07-27T06:49:24Z"}]}