{"id":3831,"title":"Despacito","body":"1.pants\n-Pulkstenis r\u0101da jau vienpadsmit vak\u0101r\u0101\n-Skatieties cik v\u0113la jau ir nakts\n-Tikko es atlidojuno Francijas\n-Un es braucu d\u012bze\u013cvilcien\u0101\n\n2.pants\n\n-Es\ntagat esmu r\u012bgas centr\u0101\n-Tikko atgriezies no kara     x2\n-Un es nezinu kur t\u0101l\u0101k j\u0101iet\n3.pants\n-L\u0113ni eju es uz Daugavgr\u012bvas pusi\n-P\u0113k\u0161\u0146i izbrauc tre\u0161ais busi\u0146\u0161\n-Un es skrienu vi\u0146am paka\u013c\n\n-\u0100tri skrienu es uz uz autobusa pusi \n-P\u0113k\u0161\u0146i busi\u0146\u0161 aizc\u0113rt durvis \n-Un vi\u0146\u0161 tinas t\u0101l\u0101k","bodyLyrics":"1.pants\n-Pulkstenis r\u0101da jau vienpadsmit vak\u0101r\u0101\n-Skatieties cik v\u0113la jau ir nakts\n-Tikko es atlidojuno Francijas\n-Un es braucu d\u012bze\u013cvilcien\u0101\n\n2.pants\n\n-Es\ntagat esmu r\u012bgas centr\u0101\n-Tikko atgriezies no kara x2\n-Un es nezinu kur t\u0101l\u0101k j\u0101iet\n3.pants\n-L\u0113ni eju es uz Daugavgr\u012bvas pusi\n-P\u0113k\u0161\u0146i izbrauc tre\u0161ais busi\u0146\u0161\n-Un es skrienu vi\u0146am paka\u013c\n\n-\u0100tri skrienu es uz uz autobusa pusi \n-P\u0113k\u0161\u0146i busi\u0146\u0161 aizc\u0113rt durvis \n-Un vi\u0146\u0161 tinas t\u0101l\u0101k","bodyAbc":"","url":"\/song\/3831-Viktors_Stupacuks_-_Despacito","youtubeLink":"","updatedDate":"2022-02-26T16:21:23Z","createdDate":"2020-05-31T06:34:53Z","songTop":{"visitsWeekly":0},"mainArtist":{"id":1444,"title":"Viktors Stupa\u010duks","url":"\/band\/1444-Viktors_Stupacuks","songCount":1,"updatedDate":"2022-02-26T16:19:11Z","createdDate":"2020-05-31T06:34:53Z"},"tags":[{"id":22,"title":"bez akordiem","url":"\/tag\/22-Bez_Akordiem","songCount":1535,"labelColor":"#95a5a6"}],"poets":[],"composers":[],"performers":[{"id":1444,"title":"Viktors Stupa\u010duks","url":"\/band\/1444-Viktors_Stupacuks","songCount":1,"updatedDate":"2022-02-26T16:19:11Z","createdDate":"2020-05-31T06:34:53Z"}]}