{"id":3530,"title":"Stars","body":"","bodyLyrics":"","bodyAbc":"","url":"\/song\/3530-Trianas_Parks_Triana_Park_-_Stars","youtubeLink":"IDYN9K5kU-k","updatedDate":"2025-01-17T20:29:27.632887Z","createdDate":"2019-06-12T12:33:17Z","songTop":{"visitsWeekly":0},"mainArtist":{"id":705,"title":"Tri\u0101nas Parks (Triana Park)","url":"\/band\/705-Trianas_Parks_Triana_Park","songCount":14,"updatedDate":"2022-10-20T11:34:26Z","createdDate":"2022-10-20T11:34:26Z"},"tags":[],"poets":null,"composers":null,"performers":null}