{"id":3613,"title":"\u0122imenes albums","body":"","bodyLyrics":"","bodyAbc":"","url":"\/song\/3613-Cikagas_Piecisi_-_Gimenes_Albums","youtubeLink":"C8gkVro7c2k","updatedDate":"2022-02-26T16:21:22Z","createdDate":"2020-04-15T06:12:06Z","songTop":{"visitsWeekly":0},"mainArtist":{"id":67,"title":"\u010cik\u0101gas piec\u012b\u0161i","url":"\/band\/67-Cikagas_Piecisi","songCount":116,"updatedDate":"2023-04-23T10:19:20.008Z","createdDate":"2022-10-22T17:35:42Z"},"tags":[],"poets":null,"composers":null,"performers":null}