{"id":4697,"title":"Dz\u012bves maldi","body":"\u013bauj aps\u0113sties pie tav\u0101m k\u0101j\u0101m,\nUn tav\u0101 kl\u0113p\u012b galvu glaust.\nTik ilgi \u0161\u0137irtus ce\u013cus g\u0101j\u0101m,\nCik ilgi to pat neapjaust.\n \n2x\nEs dz\u012bves ce\u013cos mald\u012bjos,\nGan g\u0101ju prom, gan atgriezos.\nTik ilgi \u0161\u0137irti bij\u0101m m\u0113s,\nCik ilgi to pat neapjaust.\n\nVien tevi m\u012blot sirdi skaidru,\nEs sp\u0113ju tavus ce\u013cus iet.\nTik atceroties tavu smaidu,\nEs ziedu nesp\u0113ju pat m\u012bt.\n\n2x\nEs dz\u012bves ce\u013cos mald\u012bjos,\nGan g\u0101ju prom, gan atgriezos.\nTik ilgi \u0161\u0137irti bij\u0101m m\u0113s,\nCik ilgi to pat neapjaust.\n\n\u013bauj aps\u0113sties pie tav\u0101m k\u0101j\u0101m,\nUn tav\u0101 kl\u0113p\u012b galvu glaust.\nTik ilgi \u0161\u0137irtus ce\u013cus g\u0101j\u0101m,\nCik ilgi to pat neapjaust.\n\n2x\nEs dz\u012bves ce\u013cos mald\u012bjos,\nGan g\u0101ju prom, gan atgriezos.\nTik ilgi \u0161\u0137irti bij\u0101m m\u0113s,\nCik ilgi to pat neapjaust.","bodyLyrics":"\u013bauj aps\u0113sties pie tav\u0101m k\u0101j\u0101m,\nUn tav\u0101 kl\u0113p\u012b galvu glaust.\nTik ilgi \u0161\u0137irtus ce\u013cus g\u0101j\u0101m,\nCik ilgi to pat neapjaust.\n\n2x\nEs dz\u012bves ce\u013cos mald\u012bjos,\nGan g\u0101ju prom, gan atgriezos.\nTik ilgi \u0161\u0137irti bij\u0101m m\u0113s,\nCik ilgi to pat neapjaust.\n\nVien tevi m\u012blot sirdi skaidru,\nEs sp\u0113ju tavus ce\u013cus iet.\nTik atceroties tavu smaidu,\nEs ziedu nesp\u0113ju pat m\u012bt.\n\n2x\nEs dz\u012bves ce\u013cos mald\u012bjos,\nGan g\u0101ju prom, gan atgriezos.\nTik ilgi \u0161\u0137irti bij\u0101m m\u0113s,\nCik ilgi to pat neapjaust.\n\n\u013bauj aps\u0113sties pie tav\u0101m k\u0101j\u0101m,\nUn tav\u0101 kl\u0113p\u012b galvu glaust.\nTik ilgi \u0161\u0137irtus ce\u013cus g\u0101j\u0101m,\nCik ilgi to pat neapjaust.\n\n2x\nEs dz\u012bves ce\u013cos mald\u012bjos,\nGan g\u0101ju prom, gan atgriezos.\nTik ilgi \u0161\u0137irti bij\u0101m m\u0113s,\nCik ilgi to pat neapjaust.","bodyAbc":"","url":"\/song\/4697-Emburgas_Zeni_-_Dzives_Maldi","youtubeLink":"","updatedDate":"2022-02-26T16:21:29Z","createdDate":"2020-06-14T20:17:28Z","songTop":{"visitsWeekly":0},"mainArtist":{"id":1663,"title":"Emburgas z\u0113ni","url":"\/band\/1663-Emburgas_Zeni","songCount":3,"updatedDate":"2022-02-26T16:19:11Z","createdDate":"2020-06-11T11:27:23Z"},"tags":[{"id":22,"title":"bez akordiem","url":"\/tag\/22-Bez_Akordiem","songCount":1535,"labelColor":"#95a5a6"}],"poets":[],"composers":[],"performers":[{"id":1663,"title":"Emburgas z\u0113ni","url":"\/band\/1663-Emburgas_Zeni","songCount":3,"updatedDate":"2022-02-26T16:19:11Z","createdDate":"2020-06-11T11:27:23Z"},{"id":1741,"title":"Aldis Rullis","url":"\/band\/1741-Aldis_Rullis","songCount":1,"updatedDate":"2022-02-26T16:19:11Z","createdDate":"2020-06-14T20:17:28Z"}]}