{"id":3251,"title":"K\u0101 Man B\u016bt","body":"Cik [C] daudz par daudz\r\nV\u0101rdos ir nepateikts\r\nCik [Am] daudz par mazs\r\nLaika, lai pasl\u0113ptos \r\nUn starp [F] zvaigzn\u0113m [Em] kr\u012bto\u0161\u0101m\r\n[Am] Nesaskait\u012bt\r\nTaviem [F] v\u0101rdiem [Em] pieb\u0101rst\u012bts\r\n[G] Neuzlas\u012bt\r\n\r\nK\u0101 man [F] b\u016bt\r\nK\u0101 man [C] b\u016bt\r\nK\u0101 man [G] b\u016bt\r\nKa nepa[C]gurt\r\n\r\nK\u0101 man [F] b\u016bt\r\nK\u0101 man [C] b\u016bt\r\nK\u0101 man [G] b\u016bt\r\nKa nepa[C]gurt\r\n\r\nMan [C] mazliet bail \r\nSevi ir pazaud\u0113t\r\nStarp [Am] br\u012bnumiem\r\nSmaidiem tik sap\u0146ainiem\r\nUn lai [F] b\u016btu [Em] s\u0101p\u012bg\u0101k \r\nTu [Am] izvairies \r\nUn aiz [F] v\u0101rdiem [Em] miglainiem \r\nTu [G] pasl\u0113pies\r\n\r\nK\u0101 man [F] b\u016bt\r\nK\u0101 man [C] b\u016bt\r\nK\u0101 man [G] b\u016bt\r\nKa nepa[C]gurt\r\n\r\nK\u0101 man [F] b\u016bt\r\nK\u0101 man [C] b\u016bt\r\nK\u0101 man [G] b\u016bt\r\nKa nepa[C]gurt\r\n\r\nUn lai [F] b\u016btu [Em] s\u0101p\u012bg\u0101k \r\nTu [Am] izvairies \r\nUn aiz [F] v\u0101rdiem [Em] miglainiem \r\nTu [G] pasl\u0113pies\r\n\r\nJo [F] tepat, ja [Em] ieklaus\u0101s\r\n[Am] Neatpaz\u012bt\r\nSirds ar [F] sirdi [Em] run\u0101j\u0101s \r\nTik [G] j\u0101sadzird\r\n\r\nK\u0101 man [F] b\u016bt\r\nK\u0101 man [C] b\u016bt\r\nK\u0101 man [G] b\u016bt\r\nKa nepa[C]gurt\r\n\r\nK\u0101 man [F] b\u016bt\r\nK\u0101 man [C] b\u016bt\r\nK\u0101 man [G] b\u016bt\r\nKa nepa[C]gurt","bodyLyrics":"Cik daudz par daudz\nV\u0101rdos ir nepateikts\nCik daudz par mazs\nLaika, lai pasl\u0113ptos \nUn starp zvaigzn\u0113m kr\u012bto\u0161\u0101m\nNesaskait\u012bt\nTaviem v\u0101rdiem pieb\u0101rst\u012bts\nNeuzlas\u012bt\n\nK\u0101 man b\u016bt\nK\u0101 man b\u016bt\nK\u0101 man b\u016bt\nKa nepagurt\n\nK\u0101 man b\u016bt\nK\u0101 man b\u016bt\nK\u0101 man b\u016bt\nKa nepagurt\n\nMan mazliet bail \nSevi ir pazaud\u0113t\nStarp br\u012bnumiem\nSmaidiem tik sap\u0146ainiem\nUn lai b\u016btu s\u0101p\u012bg\u0101k \nTu izvairies \nUn aiz v\u0101rdiem miglainiem \nTu pasl\u0113pies\n\nK\u0101 man b\u016bt\nK\u0101 man b\u016bt\nK\u0101 man b\u016bt\nKa nepagurt\n\nK\u0101 man b\u016bt\nK\u0101 man b\u016bt\nK\u0101 man b\u016bt\nKa nepagurt\n\nUn lai b\u016btu s\u0101p\u012bg\u0101k \nTu izvairies \nUn aiz v\u0101rdiem miglainiem \nTu pasl\u0113pies\n\nJo tepat, ja ieklaus\u0101s\nNeatpaz\u012bt\nSirds ar sirdi run\u0101j\u0101s \nTik j\u0101sadzird\n\nK\u0101 man b\u016bt\nK\u0101 man b\u016bt\nK\u0101 man b\u016bt\nKa nepagurt\n\nK\u0101 man b\u016bt\nK\u0101 man b\u016bt\nK\u0101 man b\u016bt\nKa nepagurt","bodyAbc":"","url":"\/song\/3251-Gunars_Kalnins_-_Ka_Man_But","youtubeLink":"","updatedDate":"2022-02-26T16:21:19Z","createdDate":"2018-01-15T10:55:41Z","songTop":{"visitsWeekly":1},"mainArtist":{"id":99,"title":"Gun\u0101rs Kalni\u0146\u0161","url":"\/band\/99-Gunars_Kalnins","songCount":15,"updatedDate":"2023-01-14T21:30:50.001Z","createdDate":"2008-01-29T22:00:00Z"},"tags":[],"poets":[{"id":227,"title":"M\u0101rti\u0146\u0161 Freimanis","url":"\/band\/227-Martins_Freimanis","songCount":100,"updatedDate":"2023-11-28T02:57:24.019Z","createdDate":"2011-04-16T21:00:00Z"}],"composers":[{"id":99,"title":"Gun\u0101rs Kalni\u0146\u0161","url":"\/band\/99-Gunars_Kalnins","songCount":15,"updatedDate":"2023-01-14T21:30:50.001Z","createdDate":"2008-01-29T22:00:00Z"}],"performers":[{"id":99,"title":"Gun\u0101rs Kalni\u0146\u0161","url":"\/band\/99-Gunars_Kalnins","songCount":15,"updatedDate":"2023-01-14T21:30:50.001Z","createdDate":"2008-01-29T22:00:00Z"}]}