{"id":777,"title":"Dziesma Pa Milu (Manfreds Lemanis)","body":"C         G    F                G\r\nMelodija skan ta ir dziesma pa milu\r\nC         G     F         G \r\nMili mani tu,jo es tevi milesu\r\nC         G      F              G\r\nMelodija skan ta ir serenade pa milu\r\nC           G    F              G\r\nMilas vardi skan,kurus tu teici man\r\n\r\nPiedz.\r\n      F      G              Am\r\n     Kadreiz vakara es tevi satiku\r\n     F       G               Am\r\n     Ar tevi runaju daudz ko soliju\r\n     F           G                   Am\r\n     Smaids tavs sirsnigais man loti patika        \r\n     F         G F        G  F         G  Am \r\n     Un tadel es un tadel es un tadel es  vaicaju\r\n\r\n\r\nC         G          F             G\r\nMelodija skan,tagad musu sirdis ir kopa\r\nC           G    F             G\r\nMilas vardi skan,sirds ko saka man\r\nC            G      F          G\r\nMelodija man ta ir serenade pa milu\r\nC           G    F           G\r\nMilas vardi skan vai tu tici man","bodyLyrics":"Melodija skan ta ir dziesma pa milu\nMili mani tu,jo es tevi milesu\nMelodija skan ta ir serenade pa milu\nMilas vardi skan,kurus tu teici man\n\nPiedz.\nKadreiz vakara es tevi satiku\nAr tevi runaju daudz ko soliju\nSmaids tavs sirsnigais man loti patika \nUn tadel es un tadel es un tadel es vaicaju\n\n\nMelodija skan,tagad musu sirdis ir kopa\nMilas vardi skan,sirds ko saka man\nMelodija man ta ir serenade pa milu\nMilas vardi skan vai tu tici man","bodyAbc":"","url":"\/song\/777-DAZADI_-_Dziesma_Pa_Milu","youtubeLink":"","updatedDate":"2022-02-26T16:21:06Z","createdDate":"2008-09-19T21:00:00Z","songTop":{"visitsWeekly":0},"mainArtist":{"id":39,"title":"#DA\u017d\u0100DI","url":"\/band\/39-DAZADI","songCount":23,"updatedDate":"2023-01-31T08:31:17.092Z","createdDate":"2023-01-31T08:31:17.092Z"},"tags":[],"poets":[],"composers":[],"performers":[{"id":39,"title":"#DA\u017d\u0100DI","url":"\/band\/39-DAZADI","songCount":23,"updatedDate":"2023-01-31T08:31:17.092Z","createdDate":"2023-01-31T08:31:17.092Z"}]}